CHANGES.txt
LICENSE
bootstrap.py
buildout.cfg
setup.py
versions.cfg
src/clockin/README.txt
src/clockin/__init__.py
src/clockin/calendar.py
src/clockin/clockin.py
src/clockin/config.py
src/clockin/hook.txt
src/clockin/hooks.py
src/clockin/testing.py
src/clockin/tests.py
src/clockin.egg-info/PKG-INFO
src/clockin.egg-info/SOURCES.txt
src/clockin.egg-info/dependency_links.txt
src/clockin.egg-info/entry_points.txt
src/clockin.egg-info/namespace_packages.txt
src/clockin.egg-info/requires.txt
src/clockin.egg-info/top_level.txt
src/clockin.egg-info/zip-safe
