Metadata-Version: 1.0
Name: clockin
Version: 0.1.4
Summary: command line tool to do time reporting on google calendar
Home-page: http://code.google.com/p/clockin
Author: Bernd Roessl
Author-email: bernd.roessl@gmail.com
License: Apache License 2.0
Keywords: clockin google calendar
Platform: Any
